{"name": "Audio DAC SHIM", "class": "board", "type": "audio", "formfactor": "Custom", "manufacturer": "Pimoroni", "description": "An I2S digital to line-level analog audio converter", "buy": "https://shop.pimoroni.com/products/audio-dac-shim-line-out", "image": "pimoroni-audio-dac-shim.png", "pincount": 40, "eeprom": false, "power": ["2", "4"], "ground": ["6", "9", "14", "20", "25", "30", "34", "39"], "pin": {"12": {"name": "I2S"}, "35": {"name": "I2S"}, "40": {"name": "I2S"}}, "install": {"devices": ["i2s"]}, "title": "Audio DAC SHIM", "pinout_url": ["https://pinout.xyz/pinout/audio_dac_shim"]}