{"name": "JamHat", "class": "board", "type": "multi", "formfactor": "HAT", "manufacturer": "ModMyPi", "description": "A Jam friendly board with 6 LEDs, 2 buttons and a buzzer.", "url": "https://thepihut.com/products/jam-hat", "github": "https://github.com/modmypi/Jam-HAT", "buy": "https://thepihut.com/products/jam-hat", "image": "modmypi-jamhat.png", "pincount": 40, "eeprom": false, "power": ["1", "2", "4"], "ground": ["6", "9", "14", "20", "25", "30", "34", "39"], "pin": {"29": {"name": "LED1", "direction": "output", "active": "high"}, "31": {"name": "LED2", "direction": "output", "active": "high"}, "32": {"name": "LED3", "direction": "output", "active": "high"}, "33": {"name": "LED4", "direction": "output", "active": "high"}, "36": {"name": "LED5", "direction": "output", "active": "high"}, "11": {"name": "LED6", "direction": "output", "active": "high"}, "12": {"name": "Button 2/Right Button", "direction": "input", "active": "high"}, "35": {"name": "Button 1/Left Button", "direction": "input", "active": "high"}, "38": {"name": "Buzzer", "direction": "output", "active": "high"}}, "title": "Jam Hat", "pinout_url": ["https://pinout.xyz/pinout/jamhat"]}