{"name": "MDB2Pi HAT", "class": "board", "type": "IO,Power", "formfactor": "HAT", "manufacturer": "Abrantix", "collected": "Other", "description": "Multi-Drop-Bus MDB Converter Board for the Raspberry Pi", "url": "http://blog.abrantix.com/webshop/mdb-converter/", "buy": "http://blog.abrantix.com/webshop/product/mdb-to-raspberrypi", "image": "mdb2pi-hat.png", "pincount": 40, "eeprom": true, "power": ["1", "2", "4", "17"], "ground": ["6", "9", "14", "20", "25", "30", "34", "39"], "pin": {"3": {"mode": "i2c"}, "5": {"mode": "i2c"}, "8": {"mode": "UART"}, "10": {"mode": "UART"}, "27": {"mode": "i2c"}, "28": {"mode": "i2c"}}, "i2c": {"0x50": {"name": "HAT EEPROM on I2C0", "device": "24C32"}, "0x51": {"name": "RTC on I2C1", "device": "PCF8563"}}, "title": "MDB2Pi HAT", "pinout_url": ["https://pinout.xyz/pinout/mdb2pi_hat"]}