{"name": "Unicorn pHAT", "class": "board", "type": "led", "formfactor": "pHAT", "manufacturer": "Pimoroni", "description": "32 blindingly bright RGB LEDs on a single pHAT", "url": "http://shop.pimoroni.com/products/unicorn-phat", "github": "https://github.com/pimoroni/unicornhat", "buy": "http://shop.pimoroni.com/products/unicorn-phat", "image": "unicorn-phat.png", "pincount": 40, "eeprom": true, "power": ["2"], "ground": ["6", "9", "14", "20", "25", "30", "34", "39"], "pin": {"12": {"name": "Data", "direction": "output", "mode": "pwm", "active": "high", "description": "WS2812 Data"}}, "install": {"apt": ["python-dev", "python3-dev"], "python": ["unicornhat"], "python3": ["unicornhat"]}, "title": "Unicorn pHAT", "pinout_url": ["https://pinout.xyz/pinout/unicorn_phat"]}